realmarigold_tool/__init__.py
realmarigold_tool/test.py
realmarigold_tool-0.1.0.dist-info/LICENSE
realmarigold_tool-0.1.0.dist-info/METADATA
realmarigold_tool-0.1.0.dist-info/WHEEL
realmarigold_tool-0.1.0.dist-info/top_level.txt
realmarigold_tool-0.1.0.dist-info/RECORD
